Metadata-Version: 2.1
Name: tacalendar
Version: 0.1
Summary: Handles date time manipulation with simplicity
Home-page: https://github.com/tousifanaam/tcalendar
Author: Tousif Anaam
Author-email: tousifanaam@gmail.com
License: GNU
Keywords: ttime,tcalendar,tcalendar_time,tc,tt
Platform: UNKNOWN
Classifier: Development Status :: 5 - Production/Stable
Classifier: Intended Audience :: Developers
Classifier: License :: OSI Approved :: GNU General Public License (GPL)
Classifier: Operating System :: OS Independent
Classifier: Programming Language :: Python
Classifier: Programming Language :: Python :: 3
Classifier: Programming Language :: Python :: 3.6
Classifier: Programming Language :: Python :: 3.7
Classifier: Programming Language :: Python :: 3.8
Classifier: Programming Language :: Python :: 3.9
Classifier: Programming Language :: Python :: 3 :: Only
Classifier: Topic :: Software Development :: Libraries :: Python Modules
